README.md
setup.cfg
setup.py
pyxhttp/__init__.py
pyxhttp/handlers.py
pyxhttp/handlers_test.py
pyxhttp.egg-info/PKG-INFO
pyxhttp.egg-info/SOURCES.txt
pyxhttp.egg-info/dependency_links.txt
pyxhttp.egg-info/requires.txt
pyxhttp.egg-info/top_level.txt